examples/__init__.py
examples/settings.py
examples/spiders/__init__.py
examples/spiders/auto_recaptcha.py
examples/spiders/cloudflare_captcha.py
examples/spiders/compose.py
examples/spiders/fill_form.py
examples/spiders/follow.py
examples/spiders/har.py
examples/spiders/manual_recaptcha.py
examples/spiders/meduza.py
examples/spiders/webscraperio.py
scrapy_puppeteer_client-0.4.0.dist-info/licenses/LICENSE
scrapypuppeteer/__init__.py
scrapypuppeteer/actions.py
scrapypuppeteer/middleware.py
scrapypuppeteer/request.py
scrapypuppeteer/response.py
scrapypuppeteer/browser_managers/__init__.py
scrapypuppeteer/browser_managers/playwright_browser_manager.py
scrapypuppeteer/browser_managers/pyppeteer_browser_manager.py
scrapypuppeteer/browser_managers/service_browser_manager.py
scrapy_puppeteer_client-0.4.0.dist-info/METADATA
scrapy_puppeteer_client-0.4.0.dist-info/WHEEL
scrapy_puppeteer_client-0.4.0.dist-info/top_level.txt
scrapy_puppeteer_client-0.4.0.dist-info/RECORD
