Metadata-Version: 2.4
Name: scrapy-puppeteer-client
Version: 0.4.0
Summary: A library to use Puppeteer-managed browser in Scrapy spiders
Home-page: https://github.com/ispras/scrapy-puppeteer
Author: MODIS @ ISP RAS
Maintainer: Maksim Varlamov
Maintainer-email: varlamov@ispras.ru
License: BSD
Classifier: Development Status :: 3 - Alpha
Classifier: Programming Language :: Python :: 3
Classifier: Programming Language :: Python :: 3.6
Classifier: Programming Language :: Python :: 3.7
Classifier: Programming Language :: Python :: 3.8
Classifier: Programming Language :: Python :: 3.9
Classifier: Programming Language :: Python :: 3.10
Classifier: Programming Language :: Python :: 3.11
Classifier: Framework :: Scrapy
Classifier: Intended Audience :: Developers
Classifier: Operating System :: OS Independent
Classifier: License :: OSI Approved :: BSD License
Requires-Python: >=3.6
License-File: LICENSE
Requires-Dist: scrapy>=2.6
Requires-Dist: pyppeteer
Requires-Dist: syncer
Requires-Dist: bs4
Requires-Dist: playwright
Dynamic: author
Dynamic: classifier
Dynamic: description
Dynamic: description-content-type
Dynamic: home-page
Dynamic: license
Dynamic: license-file
Dynamic: maintainer
Dynamic: maintainer-email
Dynamic: requires-dist
Dynamic: requires-python
Dynamic: summary
